django_alpinui/__init__.py
django_alpinui/apps.py
django_alpinui/templates/__init__.py
django_alpinui/templates/adivider.py
django_alpinui/templates/alpinui.py
django_alpinui/templates/alpinui_dependencies.py
django_alpinui/templatetags/__init__.py
django_alpinui/templatetags/alpinui.py
django_alpinui-0.0.4.dist-info/LICENSE
django_alpinui-0.0.4.dist-info/METADATA
django_alpinui-0.0.4.dist-info/WHEEL
django_alpinui-0.0.4.dist-info/top_level.txt
django_alpinui-0.0.4.dist-info/RECORD
