Metadata-Version: 2.1
Name: django_alpinui
Version: 0.0.4
Summary: UI component library for Django.
Author-email: Juro Oravec <juraj.oravec.josefson@gmail.com>
License: MIT
Project-URL: Homepage, https://github.com/JuroOravec/alpinui/blob/main/packages/alpinui-django
Keywords: django,css,js,html,component library,ui library,alpine,vuetify
Classifier: Framework :: Django
Classifier: Framework :: Django :: 4.2
Classifier: Framework :: Django :: 5.0
Classifier: Operating System :: OS Independent
Classifier: Programming Language :: Python
Classifier: Programming Language :: Python :: 3
Classifier: Programming Language :: Python :: 3.8
Classifier: Programming Language :: Python :: 3.9
Classifier: Programming Language :: Python :: 3.10
Classifier: Programming Language :: Python :: 3.11
Classifier: Programming Language :: Python :: 3.12
Requires-Python: <4.0,>=3.8
License-File: LICENSE
Requires-Dist: Django >=4.2
Requires-Dist: django-components >=0.84
